[
{"online":false,"host":"officeserver1.mcv.kr","port":25565,"ip_address":"172.104.117.161","eula_blocked":false,"retrieved_at":1750518246713,"expires_at":1750518306713,"srv_record":null}
,
{"online":false,"host":"officeserver2.mcv.kr","port":25565,"ip_address":"172.104.117.161","eula_blocked":false,"retrieved_at":1750518248866,"expires_at":1750518308866,"srv_record":null}
,
{"online":false,"host":"mc.hamuin.com","port":25565,"ip_address":null,"eula_blocked":false,"retrieved_at":1750518191142,"expires_at":1750518251142,"srv_record":null}
]
