[
{"online":false,"host":"officeserver1.mcv.kr","port":25565,"ip_address":"172.104.117.252","eula_blocked":false,"retrieved_at":1750680482756,"expires_at":1750680542756,"srv_record":null}
,
{"online":false,"host":"officeserver2.mcv.kr","port":25565,"ip_address":"172.104.117.252","eula_blocked":false,"retrieved_at":1750680485939,"expires_at":1750680545939,"srv_record":null}
,
{"online":false,"host":"mc.hamuin.com","port":25565,"ip_address":null,"eula_blocked":false,"retrieved_at":1750680488020,"expires_at":1750680548020,"srv_record":null}
]
