[
{"online":false,"host":"officeserver1.mcv.kr","port":25565,"ip_address":"172.104.117.237","eula_blocked":false,"retrieved_at":1749157470526,"expires_at":1749157530526,"srv_record":null}
,
{"online":false,"host":"officeserver2.mcv.kr","port":25565,"ip_address":"172.104.117.237","eula_blocked":false,"retrieved_at":1749157473260,"expires_at":1749157533260,"srv_record":null}
,
{"online":false,"host":"mc.hamuin.com","port":25565,"ip_address":null,"eula_blocked":false,"retrieved_at":1749157475128,"expires_at":1749157535128,"srv_record":null}
]
