[
{"online":false,"host":"officeserver1.mcv.kr","port":25565,"ip_address":null,"eula_blocked":false,"retrieved_at":1752723158376,"expires_at":1752723218376,"srv_record":null}
,
{"online":false,"host":"officeserver2.mcv.kr","port":25565,"ip_address":null,"eula_blocked":false,"retrieved_at":1752723159963,"expires_at":1752723219963,"srv_record":null}
,
{"online":false,"host":"mc.hamuin.com","port":25565,"ip_address":null,"eula_blocked":false,"retrieved_at":1752723162370,"expires_at":1752723222370,"srv_record":null}
]
