[
{"online":false,"host":"officeserver1.mcv.kr","port":25565,"ip_address":"172.104.117.229","eula_blocked":false,"retrieved_at":1750563068244,"expires_at":1750563128244,"srv_record":null}
,
{"online":false,"host":"officeserver2.mcv.kr","port":25565,"ip_address":"172.104.117.229","eula_blocked":false,"retrieved_at":1750563070586,"expires_at":1750563130586,"srv_record":null}
,
{"online":false,"host":"mc.hamuin.com","port":25565,"ip_address":null,"eula_blocked":false,"retrieved_at":1750563072565,"expires_at":1750563132565,"srv_record":null}
]
