[
{"online":false,"host":"officeserver1.mcv.kr","port":25565,"ip_address":"172.104.117.157","eula_blocked":false,"retrieved_at":1751965578418,"expires_at":1751965638418,"srv_record":null}
,
{"online":false,"host":"officeserver2.mcv.kr","port":25565,"ip_address":null,"eula_blocked":false,"retrieved_at":1751965580580,"expires_at":1751965640580,"srv_record":null}
,
{"online":false,"host":"mc.hamuin.com","port":25565,"ip_address":null,"eula_blocked":false,"retrieved_at":1751965582079,"expires_at":1751965642079,"srv_record":null}
]
