[
{"online":false,"host":"officeserver1.mcv.kr","port":25565,"ip_address":"172.104.117.229","eula_blocked":false,"retrieved_at":1749215564406,"expires_at":1749215624406,"srv_record":null}
,
{"online":false,"host":"officeserver2.mcv.kr","port":25565,"ip_address":"172.104.117.229","eula_blocked":false,"retrieved_at":1749215566507,"expires_at":1749215626507,"srv_record":null}
,
{"online":false,"host":"mc.hamuin.com","port":25565,"ip_address":null,"eula_blocked":false,"retrieved_at":1749215568333,"expires_at":1749215628333,"srv_record":null}
]
